burst/__init__.py
burst/blueprint.py
burst/burst.py
burst/master/__init__.py
burst/master/master.py
burst/proxy/__init__.py
burst/proxy/group_queue.py
burst/proxy/proxy.py
burst/proxy/reload_helper.py
burst/proxy/stat_counter.py
burst/proxy/task_container.py
burst/proxy/task_dispatcher.py
burst/proxy/connection/__init__.py
burst/proxy/connection/admin_connection.py
burst/proxy/connection/client_tcp_connection.py
burst/proxy/connection/client_udp_connection.py
burst/proxy/connection/master_connection.py
burst/proxy/connection/worker_connection.py
burst/share/__init__.py
burst/share/config.py
burst/share/constants.py
burst/share/log.py
burst/share/mixins.py
burst/share/six.py
burst/share/task.py
burst/share/utils.py
burst/worker/__init__.py
burst/worker/connection.py
burst/worker/request.py
burst/worker/worker.py
burst_ex-0.0.3.data/scripts/burstctl
burst_ex-0.0.3.dist-info/METADATA
burst_ex-0.0.3.dist-info/WHEEL
burst_ex-0.0.3.dist-info/top_level.txt
burst_ex-0.0.3.dist-info/RECORD
