Metadata-Version: 2.1
Name: burst-ex
Version: 0.0.3
Summary: twisted with master, proxy and worker
Home-page: https://pypi.org/project/burst-ex
Author: QFun
Author-email: code@qfun.com
License: MIT
Platform: any
Requires-Dist: setproctitle
Requires-Dist: twisted
Requires-Dist: events
Requires-Dist: netkit
Requires-Dist: click
Requires-Dist: redis
